{
  "name": "sy-tasks",
  "author": "frostime",
  "url": "https://github.com/siyuan-note/plugin-sample-vite-svelte",
  "version": "0.1.0",
  "minAppVersion": "3.0.0",
  "backends": [
    "windows",
    "linux",
    "darwin",
    "ios",
    "android",
    "harmony",
    "docker"
  ],
  "frontends": [
    "desktop",
    "mobile",
    "browser-desktop",
    "browser-mobile",
    "desktop-window"
  ],
  "displayName": {
    "default": "Task List Panel",
    "zh_CN": "任务列表面板"
  },
  "description": {
    "default": "Displays a panel listing all tasks from all notebooks.",
    "zh_CN": "显示一个面板，列出所有笔记本中的所有任务。"
  },
  "readme": {
    "en_US": "README.md",
    "zh_CN": "README_zh_CN.md"
  },
  "funding": {
    "custom": [""]
  },
  "keywords": ["tasks", "todo", "list", "obsidian", "task management"]
}
